hmac2/__init__.py
hmac2/hmac2.py
hmac2-0.0.2.dist-info/LICENSE
hmac2-0.0.2.dist-info/METADATA
hmac2-0.0.2.dist-info/WHEEL
hmac2-0.0.2.dist-info/top_level.txt
hmac2-0.0.2.dist-info/RECORD
