Metadata-Version: 2.1
Name: hmac2
Version: 0.0.2
Summary: A small test package for hmac2.
Home-page: https://github.com/pypa/sampleproject
Author: Jiage
Classifier: Programming Language :: Python :: 3
Classifier: License :: OSI Approved :: MIT License
Classifier: Operating System :: OS Independent
Requires-Python: >=3.4
License-File: LICENSE
